LICENSE
MANIFEST.in
README.md
setup.py
django_janitor.egg-info/PKG-INFO
django_janitor.egg-info/SOURCES.txt
django_janitor.egg-info/dependency_links.txt
django_janitor.egg-info/not-zip-safe
django_janitor.egg-info/requires.txt
django_janitor.egg-info/top_level.txt
janitor/__init__.py
janitor/admin.py
janitor/apps.py
janitor/forms.py
janitor/models.py
janitor/views.py
janitor/whitelists.py
janitor/management/__init__.py
janitor/management/commands/__init__.py
janitor/management/commands/clean_all.py
janitor/management/commands/clean_model.py
janitor/management/commands/list_html_elements.py
janitor/management/commands/list_html_elements_for_model.py
janitor/migrations/0001_initial.py
janitor/migrations/__init__.py
janitor/tests/__init__.py
janitor/tests/test_forms.py
janitor/tests/test_models.py