Metadata-Version: 1.1
Name: django-janitor
Version: 0.5.1
Summary: django-janitor allows you to use bleach to clean HTML stored in a Model's field.
Home-page: https://github.com/bradmontgomery/django-janitor
Author: Brad Montgomery
Author-email: brad@bradmontgomery.net
License: MIT
Platform: UNKNOWN
Classifier: Development Status :: 4 - Beta
Classifier: Environment :: Web Environment
Classifier: Framework :: Django
Classifier: Intended Audience :: Developers
Classifier: License :: OSI Approved :: MIT License
Classifier: Operating System :: OS Independent
Classifier: Programming Language :: Python
Classifier: Programming Language :: Python :: 3
Classifier: Topic :: Internet :: WWW/HTTP
Classifier: Topic :: Software Development :: Libraries :: Python Modules
Classifier: Topic :: Text Processing :: Markup :: HTML
Classifier: Topic :: Utilities
